twitter_remove_strangers/__init__.py
twitter_remove_strangers-0.1.0.dist-info/entry_points.txt
twitter_remove_strangers-0.1.0.dist-info/LICENSE
twitter_remove_strangers-0.1.0.dist-info/WHEEL
twitter_remove_strangers-0.1.0.dist-info/METADATA
twitter_remove_strangers-0.1.0.dist-info/RECORD
