Metadata-Version: 2.1
Name: twitter-remove-strangers
Version: 0.1.0
Summary: Removing followers whom you don't follow
Author: 51naa
Requires-Python: >=3.7,<4.0
Classifier: Programming Language :: Python :: 3
Classifier: Programming Language :: Python :: 3.10
Classifier: Programming Language :: Python :: 3.7
Classifier: Programming Language :: Python :: 3.8
Classifier: Programming Language :: Python :: 3.9
Requires-Dist: click (>=8.1.3,<9.0.0)
Requires-Dist: tweepy (>=4.10.0,<5.0.0)
